Workbook

Sheet Instrucoes
A1: Calculadora de Custo — Apps Migration (AVA Fabric Agents)
A2: PoC de 4 semanas · custo total com pessoas alocadas · valores em USD com conversão para BRL
B4: Como usar
B5: Preencha somente as células com fundo AMARELO. As células com fundo VERDE são calculadas — não edite.
B6: Ordem sugerida: 1) Parametros → 2) Volumetria → 3) Equipe → 4) Infraestrutura → 5) IA → 6) Resumo.
B7: O que cada aba faz
B8: 1. Parametros — semanas, horas/semana, câmbio, margem padrão, contingência, rate card por nível e baseline de referência.
B9: 2. Volumetria — LOC, módulos, integrações e telas do sistema do cliente; stack legada e tipo de migração. Produz o Combined Base Factor e as horas recomendadas.
B10: 3. Equipe — papéis alocados, horas/semana e semanas. É AQUI que o custo de pessoas é formado (horas × rate card).
B11: 4. Infraestrutura — Azure durante a PoC (runner do pipeline, ambiente DEV do BC piloto, serviços compartilhados, storage).
B12: 5. IA — custo do modelo por fase, a partir de tokens de entrada/saída medidos no run real.
B13: 6. Resumo — consolida pessoas + infraestrutura + IA, aplica contingência e apresenta o total em USD e BRL.
B14: Margem
B15: Cada linha de custo tem sua PRÓPRIA coluna de margem (%), pré-carregada com a margem padrão de Parametros!B12.
... B23: O custo de IA calculado bottom-up (aba IA) costuma ficar ABAIXO da provisão de US$ 600 usada na proposta. O Resumo adota o MAIOR dos dois, por conservadorismo.

Sheet Parametros
A1: 1. Parâmetros
A2: Células amarelas são de entrada. Este é o único lugar onde se define câmbio, margem padrão e rate card.
A4: 1.1 Identificação
A5: Cliente | B5: ABC Bank
A6: Escopo | B6: PoC 4 semanas — F0→F3S + F4 em 1 BC piloto
A7: Data da proposta | B7: 2026-08-21
A9: 1.2 Parâmetros gerais
A10: Semanas da PoC | B10: 4 | C10: Prazo contratado. Dirige horas (Equipe) e meses de infraestrutura.
A11: Horas por semana (1 FTE) | B11: 40 | C11: Base para converter alocação em FTE.
A12: Câmbio USD → BRL | B12: 5.4 | C12: Usado apenas na conversão do total no Resumo.
A13: Margem padrão por item (%) | B13: 0.2 | C13: Pré-carrega a coluna de margem de cada aba. Pode ser alterada linha a linha.
A14: Contingência sobre o total (%) | B14: 0.15 | C14: Cobre re-execução de uma fase e remediação do build gate no BC piloto.
A15: Provisão mínima de IA (US$) | B15: 600 | C15: Valor adotado na proposta. O Resumo usa o MAIOR entre este e o cálculo bottom-up.
A17: 1.3 Rate card por nível (US$/h) — SUBSTITUIR pelos valores oficiais
A18: Nível | B18: US$ / hora | C18: Observação
A19: Manager | B19: 95 | C19: Solution Architect / PM
A20: Associate Manager | B20: 78 | C20: Platform engineer / Security
A21: Team Lead / Consultant | B21: 62 | C21: Analista legado / Arquiteto TO-BE / Dev Sr.
A22: Senior Analyst | B22: 45 | C22: Dev Angular / QA / DevOps
A23: Analyst | B23: 35 | C23: Apoio
A24: Shared Service - Onshore | B24: 38 | C24: Pod da AVA Fabric Factory (blended)
A26: 1.4 Baseline de referência — execução real do pipeline (nopcommerce-04)
A27: Métrica | B27: Valor | C27: Origem
A28: Lines of Code | B28: 254001 | C28: asis/metrics.json
A29: Arquivos / unidades | B29: 1731 | C29: asis/metrics.json
A30: Integrações (APIs + plugins) | B30: 24 | C30: asis/metrics.json
A31: Telas / forms / controllers | B31: 116 | C31: asis/metrics.json
A32: Bounded contexts | B32: 10 | C32: asis/metrics.json
A33: Tasks do backlog (programa completo) | B33: 394 | C33: speckit/traceability.json
A34: Horas da PoC de referência | B34: 800 | C34: BEH Staffing — slide 8
A35: Custo de IA por task de codegen (US$) | B35: 1.58 | C35: runner-state.json (medido)
A37: 1.5 Preço do modelo de IA
A38: US$ por 1M tokens de ENTRADA | B38: 3 | C38: Tarifa pública de referência.
A39: US$ por 1M tokens de SAÍDA | B39: 15 | C39: Tarifa pública de referência.

Sheet Volumetria
A1: 2. Volumetria do sistema do cliente
A2: Dirige o dimensionamento do esforço. Comparada ao baseline, produz o Combined Base Factor.
A4: 2.1 Volumetria (entrada)
A5: Categoria | B5: Volumetria | C5: Baseline | D5: Ratio | E5: Peso | F5: Contribuição
A6: Codebase Size (unidades / módulos) | B6: 400 | C6: =Parametros!$B$29 | D6: =IFERROR(B6/C6,0) | E6: 0.1 | F6: =D6*E6
A7: Lines of Code | B7: 2028576 | C7: =Parametros!$B$28 | D7: =IFERROR(B7/C7,0) | E7: 0.5 | F7: =D7*E7
A8: Integrations | B8: 45 | C8: =Parametros!$B$30 | D8: =IFERROR(B8/C8,0) | E8: 0.2 | F8: =D8*E8
A9: Forms / Screens | B9: 776 | C9: =Parametros!$B$31 | D9: =IFERROR(B9/C9,0) | E9: 0.2 | F9: =D9*E9
A10: Índice de volumetria (soma ponderada) | E10: =SUM(E6:E9) | F10: =SUM(F6:F9)
A12: 2.2 Stack legada e tipo de migração
A13: Legacy Stack | B13: Delphi 5/7/XE | C13: Multiplicador | D13: =IFERROR(VLOOKUP($B$13,$H$14:$I$27,2,FALSE),1) | H13: Stack legada | I13: Fator
A14: Migration Type | B14: Refactor | C14: Multiplicador | D14: =IFERROR(VLOOKUP($B$14,$H$30:$I$33,2,FALSE),1) | H14: Delphi 5/7/XE | I14: 1.25
H15: VB6 6.0 | I15: 1.3
A16: 2.3 Fatores resultantes | H16: .NET 3.x 3.0-3.5 | I16: 1.1
A17: Combined Base Factor (índice × stack × tipo) | B17: =F10*D13*D14 | C17: Quantas vezes o sistema do cliente é maior/mais complexo que o baseline. | H17: .NET 4.x 4.0-4.8 | I17: 1
A18: Fator de esforço da PoC (=RAIZ do Combined Base Factor) | B18: =SQRT(B17) | C18: Sublinear: a PoC tem escopo fixo (1 BC piloto), logo não escala 1:1 com o tamanho. | H18: Clipper 5.x | I18: 1.4
A19: Horas recomendadas para a PoC | B19: =ROUND(Parametros!$B$34*B18,0) | C19: Baseline de 800 h × fator de esforço. Compare com as horas alocadas na aba Equipe. | H19: COBOL ANSI | I19: 1.5
H20: Java EE J2EE-7 | I20: 1.15
A21: 2.4 Backlog estimado (dirige o custo de IA em F4) | H21: VB.NET 2002+ | I21: 1.15
A22: Tasks estimadas — programa completo | B22: =ROUND(B7/(Parametros!$B$28/Parametros!$B$33),0) | C22: Proporcional ao LOC, calibrado em 394 tasks para 254.001 LOC. | H22: PowerBuilder 10-12 | I22: 1.35
A23: Bounded contexts estimados | B23: 10 | C23: O run de referência identificou 10 BCs em 254.001 LOC. | H23: Oracle Forms 6i-12c | I23: 1.35
A24: Tasks por bounded context | B24: =IFERROR(ROUND(B22/B23,0),0) | C24: Backlog médio de um BC do programa completo. | H24: FoxPro 2.x-9 | I24: 1.4
A25: Teto de tasks de codegen na PoC | B25: 40 | C25: Capacidade real de F4 em 4 semanas com 1 dev sênior no build gate. | H25: C# NET old 2.0-3.5 | I25: 1.1
A26: Tasks de codegen na PoC (F4) | B26: =MIN(B24,B25) | C26: Entra na aba IA como quantidade da fase F4. A PoC é time-boxed: nunca excede o teto. | H26: Cobol | I26: 1.5
H27: DB2 | I27: 1.2
A28: Cobertura do BC piloto na PoC | B28: =IFERROR(B26/B24,0) | C28: =IF(B26>=B24,"O BC piloto cabe inteiro na PoC.","A PoC cobre apenas parte do BC piloto — selecione um BC menor ou amplie o prazo.")
H29: Migration Type | I29: Fator
H30: Rehost | I30: 0.6
H31: Replatform | I31: 0.85
H32: Refactor | I32: 1
H33: Rebuild | I33: 1.25

Sheet Equipe
A1: 3. Equipe alocada e custo de pessoas
A2: Componente dominante do preço. Horas = alocação semanal × semanas da PoC (Parametros!B10).
A4: 3.1 Alocação da PoC
A5: Time | B5: Papel / Role Description | C5: Nível | D5: Aloc. (h/sem) | E5: Semanas | F5: Horas | G5: US$ / h | H5: Custo (US$) | I5: Margem % | J5: Custo c/ margem
A6: Governance Brazil | B6: Project / Program Manager | C6: Manager | D6: 10 | E6: 4 | F6: =D6*E6 | G6: =IFERROR(VLOOKUP(C6,Parametros!$A$19:$B$24,2,FALSE),0) | H6: =F6*G6 | I6: =Parametros!$B$13 | J6: =H6*(1+I6)
A7: 01 - AVA Fabric | B7: Solution Architect da esteira (F0-F3S) | C7: Manager | D7: 40 | E7: 4 | F7: =D7*E7 | G7: =IFERROR(VLOOKUP(C7,Parametros!$A$19:$B$24,2,FALSE),0) | H7: =F7*G7 | I7: =Parametros!$B$13 | J7: =H7*(1+I7)
A8: 01 - AVA Fabric | B8: Platform engineer (runner, gates) | C8: Associate Manager | D8: 20 | E8: 4 | F8: =D8*E8 | G8: =IFERROR(VLOOKUP(C8,Parametros!$A$19:$B$24,2,FALSE),0) | H8: =F8*G8 | I8: =Parametros!$B$13 | J8: =H8*(1+I8)
A9: 02 - AS-IS (F0-F1) | B9: Analista de legado (.NET / Delphi / VB) | C9: Team Lead / Consultant | D9: 40 | E9: 2 | F9: =D9*E9 | G9: =IFERROR(VLOOKUP(C9,Parametros!$A$19:$B$24,2,FALSE),0) | H9: =F9*G9 | I9: =Parametros!$B$13 | J9: =H9*(1+I9)
A10: 03 - TO-BE (F2-F3S) | B10: Arquiteto TO-BE / SpecKit | C10: Team Lead / Consultant | D10: 40 | E10: 2 | F10: =D10*E10 | G10: =IFERROR(VLOOKUP(C10,Parametros!$A$19:$B$24,2,FALSE),0) | H10: =F10*G10 | I10: =Parametros!$B$13 | J10: =H10*(1+I10)
A11: 04 - Codegen (F4) | B11: Dev sênior .NET (build gate) | C11: Team Lead / Consultant | D11: 40 | E11: 2 | F11: =D11*E11 | G11: =IFERROR(VLOOKUP(C11,Parametros!$A$19:$B$24,2,FALSE),0) | H11: =F11*G11 | I11: =Parametros!$B$13 | J11: =H11*(1+I11)
A12: 04 - Codegen (F4) | B12: Dev Angular | C12: Senior Analyst | D12: 20 | E12: 1 | F12: =D12*E12 | G12: =IFERROR(VLOOKUP(C12,Parametros!$A$19:$B$24,2,FALSE),0) | H12: =F12*G12 | I12: =Parametros!$B$13 | J12: =H12*(1+I12)
A13: 05 - QA (F5) | B13: QA engineer | C13: Senior Analyst | D13: 20 | E13: 1 | F13: =D13*E13 | G13: =IFERROR(VLOOKUP(C13,Parametros!$A$19:$B$24,2,FALSE),0) | H13: =F13*G13 | I13: =Parametros!$B$13 | J13: =H13*(1+I13)
A14: 06 - DevOps (F6) | B14: DevOps / IaC (Terraform) | C14: Senior Analyst | D14: 20 | E14: 1 | F14: =D14*E14 | G14: =IFERROR(VLOOKUP(C14,Parametros!$A$19:$B$24,2,FALSE),0) | H14: =F14*G14 | I14: =Parametros!$B$13 | J14: =H14*(1+I14)
A15: 07 - Security (F7) | B15: Security & compliance (LGPD / OWASP) | C15: Associate Manager | D15: 20 | E15: 3 | F15: =D15*E15 | G15: =IFERROR(VLOOKUP(C15,Parametros!$A$19:$B$24,2,FALSE),0) | H15: =F15*G15 | I15: =Parametros!$B$13 | J15: =H15*(1+I15)
A16: AVA Fabric Factory | B16: Execução do pipeline — 110 agentes, 9 fases | C16: Shared Service - Onshore | D16: 40 | E16: 4 | F16: =D16*E16 | G16: =IFERROR(VLOOKUP(C16,Parametros!$A$19:$B$24,2,FALSE),0) | H16: =F16*G16 | I16: =Parametros!$B$13 | J16: =H16*(1+I16)
A17: TOTAL | B17: =COUNTA(B6:B16)&" papéis · PoC de "&TEXT(Parametros!$B$10,"0")&" semanas" | F17: =SUM(F6:F16) | H17: =SUM(H6:H16) | I17: =IFERROR(J17/H17-1,0) | J17: =SUM(J6:J16)
A19: 3.2 Indicadores da equipe
A20: FTE médio na PoC | B20: =IFERROR(Equipe!$F$17/(Parametros!$B$10*Parametros!$B$11),0) | C20: Horas totais ÷ (semanas × horas por semana)
A21: Custo médio por hora (com margem) | B21: =IFERROR(Equipe!$J$17/Equipe!$F$17,0) | C21: Taxa efetiva de venda da hora
A22: Horas recomendadas pela volumetria | B22: =Volumetria!$B$19 | C22: Vem da aba Volumetria (baseline 800 h × fator de esforço)
A23: Aderência (alocado ÷ recomendado) | B23: =IFERROR(Equipe!$F$17/Volumetria!$B$19,0) | C23: =IF(Equipe!$F$17>=Volumetria!$B$19,"OK — alocação cobre o dimensionamento","ATENÇÃO — alocação abaixo do recomendado: reduza escopo ou aumente o time")
A24: FTE necessário para cobrir o recomendado | B24: =IFERROR(Volumetria!$B$19/(Parametros!$B$10*Parametros!$B$11),0) | C24: Quantas pessoas em tempo integral o dimensionamento pediria no mesmo prazo

Sheet Infraestrutura
A1: 4. Infraestrutura Azure durante a PoC
A2: Repassada a custo. Meses = semanas da PoC ÷ 4,345.
A4: 4.1 Itens de infraestrutura
A5: Item | B5: Qtd | C5: US$ / mês | D5: Meses | E5: Custo (US$) | F5: Margem % | G5: Custo c/ margem
A6: Pipeline runner VM (Standard D8s v5, ~730 h/mês) | B6: 1 | C6: 280 | D6: =Parametros!$B$10/4.345 | E6: =B6*C6*D6 | F6: =Parametros!$B$13 | G6: =E6*(1+F6) | H6: Executa a esteira de agentes
A7: Ambiente DEV do bounded context piloto | B7: 1 | C7: 65 | D7: =Parametros!$B$10/4.345 | E7: =B7*C7*D7 | F7: =Parametros!$B$13 | G7: =E7*(1+F7) | H7: App Service + SQL + Redis (dimensionamento DEV)
A8: Serviços compartilhados (ACR + Log Analytics) | B8: 1 | C8: 45 | D8: =Parametros!$B$10/4.345 | E8: =B8*C8*D8 | F8: =Parametros!$B$13 | G8: =E8*(1+F8) | H8: Registry e workspace de logs
A9: Storage de artefatos e egress | B9: 1 | C9: 10 | D9: =Parametros!$B$10/4.345 | E9: =B9*C9*D9 | F9: =Parametros!$B$13 | G9: =E9*(1+F9) | H9: 232 artefatos / 82 MB no run de referência
A10: TOTAL INFRAESTRUTURA | E10: =SUM(E6:E9) | G10: =SUM(G6:G9)
A12: Referência do programa completo (fora da PoC) | B12: 1410 | H12: US$/mês com DEV + STG + PROD + compartilhados = US$ 16.920/ano (azure-infra-estimator do run real)

Sheet IA
A1: 5. Custo do modelo de IA
A2: Bottom-up por fase, a partir de tokens medidos. F4 usa a quantidade de tasks da aba Volumetria.
A4: 5.1 Consumo por fase
A5: Fase | B5: Execuções / Tasks | C5: Tokens entrada (médio) | D5: Tokens saída (médio) | E5: Custo entrada | F5: Custo saída | G5: Custo (US$) | H5: Margem % | I5: Custo c/ margem
A6: F0-F1 · AS-IS Diagnostic | B6: 8 | C6: 700000 | D6: 60000 | E6: =B6*C6/1000000*Parametros!$B$38 | F6: =B6*D6/1000000*Parametros!$B$39 | G6: =E6+F6 | H6: =Parametros!$B$13 | I6: =G6*(1+H6) | J6: 7 agentes + extração AST
A7: F2 · TO-BE Architecture | B7: 3 | C7: 800000 | D7: 90000 | E7: =B7*C7/1000000*Parametros!$B$38 | F7: =B7*D7/1000000*Parametros!$B$39 | G7: =E7+F7 | H7: =Parametros!$B$13 | I7: =G7*(1+H7) | J7: 3 orquestradores
A8: F3 · Protótipo | B8: 1 | C8: 400000 | D8: 60000 | E8: =B8*C8/1000000*Parametros!$B$38 | F8: =B8*D8/1000000*Parametros!$B$39 | G8: =E8+F8 | H8: =Parametros!$B$13 | I8: =G8*(1+H8) | J8: 1 agente
A9: F3S · SpecKit | B9: 15 | C9: 500000 | D9: 90000 | E9: =B9*C9/1000000*Parametros!$B$38 | F9: =B9*D9/1000000*Parametros!$B$39 | G9: =E9+F9 | H9: =Parametros!$B$13 | I9: =G9*(1+H9) | J9: constitution + specs + plans + tasks + compliance
A10: F4 · Codegen (BC piloto) | B10: =Volumetria!$B$26 | C10: 239619 | D10: 57345 | E10: =B10*C10/1000000*Parametros!$B$38 | F10: =B10*D10/1000000*Parametros!$B$39 | G10: =E10+F10 | H10: =Parametros!$B$13 | I10: =G10*(1+H10) | J10: MEDIDO: 239.619 in / 45–69k out por task
A11: Subtotal | G11: =SUM(G6:G10) | I11: =SUM(I6:I10)
A12: Buffer de re-execução (%) | B12: 0.3 | I12: =I11*B12 | J12: Gates reprovados, reprocessamento de fase e remediação de build
A13: Custo de IA calculado (bottom-up) | I13: =I11+I12
A14: Provisão mínima adotada na proposta | I14: =Parametros!$B$15*(1+Parametros!$B$13) | J14: Parametros!B15 (US$ 600) — provisão conservadora do slide 9
A15: CUSTO DE IA ADOTADO (maior entre calculado e provisão) | I15: =MAX(I13,I14)
A17: Referência medida | B17: =IFERROR(G10/B10,0) | J17: Custo por task de codegen — o run real mediu US$ 1,58
A18: Migração completa (todas as tasks) | B18: =IFERROR(G10/B10*Volumetria!$B$22,0) | J18: Projeção só de codegen para o programa inteiro — fora do escopo da PoC

Sheet Resumo
A1: 6. Resumo — Custo total da PoC
A2: Consolida pessoas + infraestrutura + IA, aplica contingência e converte para BRL.
A4: 6.1 Escopo dimensionado
A5: Semanas da PoC | B5: =Parametros!$B$10
A6: Horas totais alocadas | B6: =Equipe!$F$17
A7: FTE médio | B7: =IFERROR(Equipe!$F$17/(Parametros!$B$10*Parametros!$B$11),0)
A8: Papéis alocados | B8: =COUNTA(Equipe!B6:B16)
A9: Combined Base Factor da volumetria | B9: =Volumetria!$B$17
A10: Horas recomendadas pela volumetria | B10: =Volumetria!$B$19
A11: Tasks de codegen na PoC (F4) | B11: =Volumetria!$B$26
A13: 6.2 Composição do custo
A14: Componente | B14: Custo com margem (US$) | C14: % do subtotal | D14: Custo (BRL) | E14: Base de cálculo
A15: Pessoas — equipe alocada | B15: =Equipe!$J$17 | C15: =IFERROR(B15/$B$18,0) | D15: =B15*Parametros!$B$12 | E15: Horas × rate card por nível (aba Equipe)
A16: Infraestrutura Azure | B16: =Infraestrutura!$G$10 | C16: =IFERROR(B16/$B$18,0) | D16: =B16*Parametros!$B$12 | E16: Runner + DEV do BC piloto + compartilhados + storage (aba Infraestrutura)
A17: Modelo de IA | B17: =IA!$I$15 | C17: =IFERROR(B17/$B$18,0) | D17: =B17*Parametros!$B$12 | E17: Tokens por fase, com buffer de re-execução (aba IA)
A18: SUBTOTAL | B18: =SUM(B15:B17) | C18: =1 | D18: =B18*Parametros!$B$12
A19: Contingência | B19: =B18*Parametros!$B$14 | C19: =Parametros!$B$14 | D19: =B19*Parametros!$B$12 | E19: Re-execução de uma fase e remediação do build gate no BC piloto (risco Beta do F4)
A20: PREÇO TOTAL DA PoC | B20: =B18+B19 | D20: =B20*Parametros!$B$12
A22: 6.3 Indicadores
A23: Preço por hora alocada (US$) | B23: =IFERROR(Resumo!$B$20/Equipe!$F$17,0) | E23: Taxa efetiva de venda, já com infraestrutura, IA e contingência
A24: Preço por semana (US$) | B24: =IFERROR(Resumo!$B$20/Parametros!$B$10,0) | E24: Custo semanal da PoC
A25: Margem embutida (US$) | B25: =B15-Equipe!$H$17+B16-Infraestrutura!$E$10+B17-IA!$G$11 | E25: Diferença entre custo com margem e custo bruto
A26: Infra + IA como % do total | B26: =IFERROR((B16+B17)/Resumo!$B$20,0) | E26: No run de referência ficou abaixo de 1%: o preço é dirigido por pessoas, não por tokens
A27: Aderência das horas (alocado ÷ recomendado) | B27: =IFERROR(Equipe!$F$17/Volumetria!$B$19,0) | E27: Abaixo de 100% indica escopo maior que a capacidade alocada
A28: FTE alocado | B28: =IFERROR(Equipe!$F$17/(Parametros!$B$10*Parametros!$B$11),0) | E28: Pessoas em tempo integral efetivamente contratadas
A29: FTE necessário pela volumetria | B29: =IFERROR(Volumetria!$B$19/(Parametros!$B$10*Parametros!$B$11),0) | E29: Se maior que o alocado, o escopo precisa ser reduzido ou o time ampliado
A31: Status do dimensionamento | B31: =IF(Equipe!$F$17>=Volumetria!$B$19,"OK","REVISAR") | E31: =IF(Equipe!$F$17>=Volumetria!$B$19,"Alocação compatível com a volumetria informada.","Volumetria acima da capacidade alocada: reduza o escopo da PoC, aumente o time ou renegocie o prazo.")

Sheet Drivers
A1: 7. Drivers de precificação (referência)
A2: Seção 6.1 do dossiê da PoC. Define o que faz o preço variar de um cliente para outro.
A4: 7.1 Drivers
A5: Driver | B5: Métrica | C5: Impacto | D5: Onde entra na calculadora
A6: Tamanho da base legada | B6: KLOC / nº de arquivos | C6: Custo de F0–F1 (linear) | D6: Volumetria B6 e B7
A7: Complexidade de domínio | B7: nº de Bounded Contexts | C7: Custo de F2–F3S | D7: Volumetria — % do backlog no BC piloto (B23)
A8: Volume de backlog | B8: nº de tasks / FP | C8: Custo de F4 (linear por task) | D8: Volumetria B22 e B24 → aba IA, fase F4
A9: Escopo de segurança | B9: security_enabled_*, SAST/DAST, pentest | C9: Custo de F1-sec e F7 | D9: Equipe — papel de Security & compliance
A10: Stacks-alvo | B10: 1 backend + 1 frontend vs. múltiplas | C10: Complexidade de F4 | D10: Equipe — devs de codegen; Volumetria — Migration Type
A11: Nuvem e ambientes | B11: Azure/AWS/GCP × dev/hml/prd | C11: Custo de F6 | D11: Aba Infraestrutura
A12: Modo de execução | B12: SaaS Avanade vs. on-premise / VPC do banco | C12: Setup e compliance | D12: Equipe — Platform engineer; margem por item
A14: 7.2 Baseline medido — run real nopcommerce-04 (18–19/08/2026)
A15: 254.001 LOC · 1.731 arquivos · 1.998 classes | B15: asis/metrics.json
A16: 15.785 procedimentos · 436 regras de negócio catalogadas | B16: brs/business_rules_catalog.json
A17: 10 bounded contexts · 2 god services | B17: asis/metrics.json
A18: 394 tasks · 2.991 arestas de dependência · 15 ondas | B18: speckit/traceability.json
A19: 232 artefatos / 82 MB · F0→F3S em ≈ 2 h 20 min de máquina | B19: pipeline_runner/
A20: US$ 1,58 por task de codegen (239.619 in / 45–69k out) | B20: runner-state.json
A21: Estimativa formal do programa: 3.323 h · 892 FP · 1.606 SP | B21: tobe/docs/effort-calculator.md
A22: Infraestrutura do programa completo: US$ 1.410/mês | B22: azure-infra-estimator_reportV1.md
